ringmaster/__init__.py
ringmaster/api.py
ringmaster/aws.py
ringmaster/cli.py
ringmaster/cloudflare.py
ringmaster/constants.py
ringmaster/k8s.py
ringmaster/res/system_info.txt
ringmaster/snowflake.py
ringmaster/util.py
ringmaster/version.py
ringmaster.show-0.4.2.dist-info/entry_points.txt
ringmaster.show-0.4.2.dist-info/LICENSE
ringmaster.show-0.4.2.dist-info/WHEEL
ringmaster.show-0.4.2.dist-info/METADATA
ringmaster.show-0.4.2.dist-info/RECORD
