Metadata-Version: 2.1
Name: ringmaster.show
Version: 0.4.2
Summary: The world is a circus and you are the ringmaster!
Home-page: https://ringmaster.show
License: Apache 2.0
Author: Geoff Williams
Author-email: geoff@declarativesystems.com
Requires-Python: >=3.8,<4.0
Classifier: License :: Other/Proprietary License
Classifier: Programming Language :: Python :: 3
Classifier: Programming Language :: Python :: 3.8
Classifier: Programming Language :: Python :: 3.9
Requires-Dist: Jinja2 (>=2.11.3,<3.0.0)
Requires-Dist: boto3 (>=1.17.24,<2.0.0)
Requires-Dist: cfn-flip (>=1.2.3,<2.0.0)
Requires-Dist: docopt (>=0.6.2,<0.7.0)
Requires-Dist: halo (>=0.0.31,<0.0.32)
Requires-Dist: loguru (>=0.5.3,<0.6.0)
Requires-Dist: python-cloudflare (>=1.0.1,<2.0.0)
Requires-Dist: python-dateutil (>=2.8.1,<3.0.0)
Requires-Dist: snakecase (>=1.0.1,<2.0.0)
Requires-Dist: snowflake-connector-python (>=2.4.1,<3.0.0)
Project-URL: Documentation, https://ringmaster.show/
Project-URL: Repository, https://github.com/declarativesystems/ringmaster
